abba_python/__init__.py
abba_python/abba.py
abba_python/abba_atlas.py
abba_python/abba_map.py
abba_python/abba_ontology.py
abba_python/py.typed
abba_python-0.10.7.dist-info/METADATA
abba_python-0.10.7.dist-info/WHEEL
abba_python-0.10.7.dist-info/licenses/LICENSE
abba_python-0.10.7.dist-info/RECORD
