Metadata-Version: 2.4
Name: abba-python
Version: 0.10.7
Summary: Aligning Big Brains and Atlases (ABBA), controlled from python.
Project-URL: homepage, https://github.com/BIOP/abba-python
Project-URL: repository, https://github.com/BIOP/abba-python
Author-email: Nicolas Chiaruttini <nicolas.chiaruttini@epfl.ch>
License: BSD-3-Clause
License-File: LICENSE
Classifier: Development Status :: 3 - Alpha
Classifier: License :: OSI Approved :: BSD License
Classifier: Programming Language :: Python :: 3
Classifier: Programming Language :: Python :: 3.9
Classifier: Programming Language :: Python :: 3.10
Classifier: Programming Language :: Python :: 3.11
Classifier: Programming Language :: Python :: 3.12
Classifier: Typing :: Typed
Requires-Python: >=3.9
Requires-Dist: brainglobe-atlasapi
Requires-Dist: pyimagej
Provides-Extra: dev
Requires-Dist: ipython; extra == 'dev'
Requires-Dist: mypy; extra == 'dev'
Requires-Dist: pdbpp; extra == 'dev'
Requires-Dist: pre-commit; extra == 'dev'
Requires-Dist: rich; extra == 'dev'
Requires-Dist: ruff; extra == 'dev'
Provides-Extra: test
Requires-Dist: pytest; extra == 'test'
Requires-Dist: pytest-cov; extra == 'test'
